zope.app.wsgi-5.3-py3.11-nspkg.pth
zope/app/wsgi/README.txt
zope/app/wsgi/__init__.py
zope/app/wsgi/configure.zcml
zope/app/wsgi/fileresult.py
zope/app/wsgi/fileresult.txt
zope/app/wsgi/filereturns.txt
zope/app/wsgi/ftesting.zcml
zope/app/wsgi/interfaces.py
zope/app/wsgi/paste.py
zope/app/wsgi/paste.txt
zope/app/wsgi/testing.py
zope/app/wsgi/testlayer.py
zope/app/wsgi/testlayer.txt
zope/app/wsgi/tests.py
zope.app.wsgi-5.3.dist-info/LICENSE.txt
zope.app.wsgi-5.3.dist-info/METADATA
zope.app.wsgi-5.3.dist-info/WHEEL
zope.app.wsgi-5.3.dist-info/entry_points.txt
zope.app.wsgi-5.3.dist-info/namespace_packages.txt
zope.app.wsgi-5.3.dist-info/top_level.txt
zope.app.wsgi-5.3.dist-info/RECORD
