Metadata-Version: 2.1
Name: zope.app.wsgi
Version: 5.3
Summary: WSGI application for the zope.publisher
Home-page: https://github.com/zopefoundation/zope.app.wsgi
Author: Zope Foundation and Contributors
Author-email: zope-dev@zope.org
License: ZPL 2.1
Project-URL: Issue Tracker, https://github.com/zopefoundation/zope.app.wsgi/issues
Project-URL: Sources, https://github.com/zopefoundation/zope.app.wsgi
Classifier: Development Status :: 5 - Production/Stable
Classifier: Environment :: Web Environment
Classifier: Intended Audience :: Developers
Classifier: License :: OSI Approved :: Zope Public License
Classifier: Programming Language :: Python
Classifier: Programming Language :: Python :: 3
Classifier: Programming Language :: Python :: 3.8
Classifier: Programming Language :: Python :: 3.9
Classifier: Programming Language :: Python :: 3.10
Classifier: Programming Language :: Python :: 3.11
Classifier: Programming Language :: Python :: 3.12
Classifier: Programming Language :: Python :: 3.13
Classifier: Programming Language :: Python :: Implementation
Classifier: Programming Language :: Python :: Implementation :: CPython
Classifier: Programming Language :: Python :: Implementation :: PyPy
Classifier: Natural Language :: English
Classifier: Operating System :: OS Independent
Classifier: Topic :: Internet :: WWW/HTTP :: WSGI :: Application
Classifier: Framework :: Zope :: 3
Requires-Python: >=3.8
License-File: LICENSE.txt
Requires-Dist: setuptools
Requires-Dist: ZConfig
Requires-Dist: legacy-cgi; python_version >= "3.13"
Requires-Dist: transaction
Requires-Dist: zope.app.appsetup>=4.0
Requires-Dist: zope.processlifetime
Requires-Dist: zope.app.publication>=4.0
Requires-Dist: zope.event
Requires-Dist: zope.interface
Requires-Dist: zope.publisher>=4.0.0a3
Requires-Dist: zope.security>4.0.0a2
Requires-Dist: zope.component
Requires-Dist: zope.container>=4.0.0a1
Requires-Dist: zope.site>=4.0.0a1
Requires-Dist: zope.traversing>=4.0.0a1
Provides-Extra: test
Requires-Dist: WebTest; extra == "test"
Requires-Dist: zope.authentication; extra == "test"
Requires-Dist: zope.browserpage; extra == "test"
Requires-Dist: zope.principalregistry>=4.0.0a1; extra == "test"
Requires-Dist: zope.securitypolicy>=4.0.0a1; extra == "test"
Requires-Dist: zope.testing; extra == "test"
Requires-Dist: zope.testrunner; extra == "test"
Provides-Extra: testlayer
Requires-Dist: WebTest; extra == "testlayer"
